{
  "appPageId" : "84dc502a-dd43-4058-96b7-951f47314b33",
  "componentName" : "siteforce:sldsOneColLayout",
  "id" : "626c55f9-c117-4781-8b55-208e040296f4",
  "label" : "Quick Order",
  "regions" : [ {
    "id" : "7eedc7b8-5a6c-450d-b4f6-590c75e6ab49",
    "regionName" : "header",
    "type" : "region"
  }, {
    "components" : [ {
      "componentAttributes" : {
        "addEntryText" : "Add Line",
        "addToCartButtonBackgroundColor" : "",
        "addToCartButtonBackgroundHoverColor" : "",
        "addToCartButtonBorderColor" : "",
        "addToCartButtonBorderRadius" : "0",
        "addToCartButtonDisabledBackgroundColor" : "rgb(201, 199, 197)",
        "addToCartButtonText" : "ADD TO CART",
        "addToCartButtonTextColor" : "",
        "addToCartButtonTextHoverColor" : "",
        "numberOfLineItemsToAddEachTime" : 1,
        "numberOfLineItemsToStart" : 5,
        "productPlaceholderText" : "Item SKU",
        "productText" : "Product",
        "quantityText" : "Quantity",
        "showAddEntryIcon" : true,
        "title" : "Quick Order"
      },
      "componentName" : "b2b_buyer_builder:quickOrderPage",
      "id" : "de89e45a-3683-42a0-a4ce-c88b330f658e",
      "renderPriority" : "NEUTRAL",
      "renditionMap" : { },
      "type" : "component"
    } ],
    "id" : "4d2571e5-2efe-4277-8e6c-454a12899966",
    "regionName" : "content",
    "type" : "region"
  }, {
    "id" : "bb449703-ba80-49d0-a688-dfd644c59e68",
    "regionName" : "footer",
    "type" : "region"
  } ],
  "themeLayoutType" : "Inner",
  "type" : "view",
  "viewType" : "quickorder"
}